audiotextspeakerchangedetect/__init__.py
audiotextspeakerchangedetect/main.py
audiotextspeakerchangedetect/sample_run.py
audiotextspeakerchangedetect/sample_run_existingllama2output.py
audiotextspeakerchangedetect/EnsembleSpeakerChangeDetection/__init__.py
audiotextspeakerchangedetect/EnsembleSpeakerChangeDetection/ensemble_detection.py
audiotextspeakerchangedetect/EnsembleSpeakerChangeDetection/helpers.py
audiotextspeakerchangedetect/SpeakerChangeDetection/__init__.py
audiotextspeakerchangedetect/SpeakerChangeDetection/helpers.py
audiotextspeakerchangedetect/SpeakerChangeDetection/speaker_change_detection_main_function.py
audiotextspeakerchangedetect/SpeakerChangeDetection/Llama2/__init__.py
audiotextspeakerchangedetect/SpeakerChangeDetection/Llama2/speaker_change_detection_llama2.py
audiotextspeakerchangedetect/SpeakerChangeDetection/Llama2/huggingface_offline/LLaMA_HuggingFace_Offline.py
audiotextspeakerchangedetect/SpeakerChangeDetection/Llama2/huggingface_offline/__init__.py
audiotextspeakerchangedetect/SpeakerChangeDetection/Llama2/prompts/__init__.py
audiotextspeakerchangedetect/SpeakerChangeDetection/Llama2/prompts/prompt1.py
audiotextspeakerchangedetect/SpeakerChangeDetection/Llama2/prompts/prompt1_template.py
audiotextspeakerchangedetect/SpeakerChangeDetection/NLP/__init__.py
audiotextspeakerchangedetect/SpeakerChangeDetection/NLP/speaker_change_detection_nlp.py
audiotextspeakerchangedetect/SpeakerChangeDetection/PyAnnote/__init__.py
audiotextspeakerchangedetect/SpeakerChangeDetection/PyAnnote/speaker_change_detection_pyannote.py
audiotextspeakerchangedetect/SpeakerChangeDetection/SpectralClustering/__init__.py
audiotextspeakerchangedetect/SpeakerChangeDetection/SpectralClustering/speaker_change_detection_clustering.py
audiotextspeakerchangedetect-1.3.0.dist-info/LICENSE
audiotextspeakerchangedetect-1.3.0.dist-info/METADATA
audiotextspeakerchangedetect-1.3.0.dist-info/WHEEL
audiotextspeakerchangedetect-1.3.0.dist-info/top_level.txt
audiotextspeakerchangedetect-1.3.0.dist-info/RECORD
