Metadata-Version: 2.1
Name: audiotextspeakerchangedetect
Version: 1.3.0
Summary: A Package to Detect Speaker Change based on Textual Features via LLMs & Rule-Based NLP and Audio Features via Pyannote & Spectral Clustering
Author-email: "Junying (Alice) Fang" <jf3375@princeton.edu>
Project-URL: Homepage, https://github.com/princeton-ddss/AudioAndTextBasedSpeakerChangeDetection
Classifier: Programming Language :: Python :: 3
Classifier: License :: OSI Approved :: MIT License
Classifier: Operating System :: OS Independent
Requires-Python: >=3.7
License-File: LICENSE
Requires-Dist: accelerate
Requires-Dist: torch
Requires-Dist: torchvision
Requires-Dist: huggingface-hub
Requires-Dist: spacy
Requires-Dist: resemblyzer
Requires-Dist: spectralcluster
Requires-Dist: transformers
Requires-Dist: pyannote.audio ==3.1.1
Requires-Dist: pyannote.core ==5.0.0
Requires-Dist: pyannote.database ==5.0.1
Requires-Dist: pyannote.metrics ==3.2.1
Requires-Dist: pyannote.pipeline ==3.0.1
